hpeOneView/__init__.py
hpeOneView/connection.py
hpeOneView/exceptions.py
hpeOneView/oneview_client.py
hpeOneView/resources/__init__.py
hpeOneView/resources/resource.py
hpeOneView/resources/task_monitor.py
hpeOneView/resources/activity/__init__.py
hpeOneView/resources/activity/alerts.py
hpeOneView/resources/activity/events.py
hpeOneView/resources/activity/tasks.py
hpeOneView/resources/data_services/__init__.py
hpeOneView/resources/data_services/metric_streaming.py
hpeOneView/resources/facilities/__init__.py
hpeOneView/resources/facilities/datacenters.py
hpeOneView/resources/facilities/power_devices.py
hpeOneView/resources/facilities/racks.py
hpeOneView/resources/fc_sans/__init__.py
hpeOneView/resources/fc_sans/endpoints.py
hpeOneView/resources/fc_sans/managed_sans.py
hpeOneView/resources/fc_sans/san_managers.py
hpeOneView/resources/fc_sans/san_providers.py
hpeOneView/resources/hypervisors/__init__.py
hpeOneView/resources/hypervisors/hypervisor_cluster_profiles.py
hpeOneView/resources/hypervisors/hypervisor_managers.py
hpeOneView/resources/networking/__init__.py
hpeOneView/resources/networking/connection_templates.py
hpeOneView/resources/networking/ethernet_networks.py
hpeOneView/resources/networking/fabrics.py
hpeOneView/resources/networking/fc_networks.py
hpeOneView/resources/networking/fcoe_networks.py
hpeOneView/resources/networking/interconnect_link_topologies.py
hpeOneView/resources/networking/interconnect_types.py
hpeOneView/resources/networking/interconnects.py
hpeOneView/resources/networking/internal_link_sets.py
hpeOneView/resources/networking/logical_downlinks.py
hpeOneView/resources/networking/logical_interconnect_groups.py
hpeOneView/resources/networking/logical_interconnects.py
hpeOneView/resources/networking/logical_switch_groups.py
hpeOneView/resources/networking/logical_switches.py
hpeOneView/resources/networking/network_sets.py
hpeOneView/resources/networking/sas_interconnect_types.py
hpeOneView/resources/networking/sas_interconnects.py
hpeoneview-11.0.0.dist-info/licenses/LICENSE
hpeoneview-11.0.0.dist-info/METADATA
hpeoneview-11.0.0.dist-info/WHEEL
hpeoneview-11.0.0.dist-info/top_level.txt
hpeoneview-11.0.0.dist-info/RECORD
