Metadata-Version: 2.4
Name: hpeOneView
Version: 11.0.0
Summary: HPE OneView Python Library
Home-page: https://github.com/HewlettPackard/oneview-python
Download-URL: https://github.com/HewlettPackard/oneview-python/tarball/v8.6.0
Author: Hewlett Packard Enterprise Development LP
Author-email: pdl-oneview-sdk@hpe.com
License: Apache
Keywords: oneview,hpe
License-File: LICENSE
Requires-Dist: future>=0.15.2
Requires-Dist: docutils<0.18
Dynamic: author
Dynamic: author-email
Dynamic: description-content-type
Dynamic: download-url
Dynamic: home-page
Dynamic: keywords
Dynamic: license
Dynamic: license-file
Dynamic: requires-dist
Dynamic: summary
